boudy_tookit/__init__.py
boudy_tookit/toolkit.py
boudy_toolkit-0.1.2.dist-info/LICENSE
boudy_toolkit-0.1.2.dist-info/METADATA
boudy_toolkit-0.1.2.dist-info/WHEEL
boudy_toolkit-0.1.2.dist-info/top_level.txt
boudy_toolkit-0.1.2.dist-info/RECORD
