Metadata-Version: 2.2
Name: boudy_toolkit
Version: 0.1.2
Summary: A comprehensive toolkit for GUI applications and system utilities
Author-email: Boudy <gamezygamer10@gmail.com>
License: MIT License
Keywords: gui,toolkit,utilities
Classifier: Programming Language :: Python :: 3
Classifier: License :: OSI Approved :: MIT License
Classifier: Operating System :: OS Independent
Requires-Python: >=3.7
License-File: LICENSE
Requires-Dist: pillow
Requires-Dist: psutil
Requires-Dist: requests
Requires-Dist: plyer
Requires-Dist: qrcode
Requires-Dist: playsound
Requires-Dist: pyttsx3
